[
    {
        "name": "Tatooine",
        "rotation_period": "23",
        "orbital_period": "304",
        "diameter": "10465",
        "climate": "arid",
        "gravity": "1 standard",
        "terrain": "desert",
        "surface_water": "1",
        "population": "200000",
        "residents": [
            "https://swapi-trybe.herokuapp.com/api/people/1/",
            "https://swapi-trybe.herokuapp.com/api/people/2/",
            "https://swapi-trybe.herokuapp.com/api/people/4/",
            "https://swapi-trybe.herokuapp.com/api/people/6/",
            "https://swapi-trybe.herokuapp.com/api/people/7/",
            "https://swapi-trybe.herokuapp.com/api/people/8/",
            "https://swapi-trybe.herokuapp.com/api/people/9/",
            "https://swapi-trybe.herokuapp.com/api/people/11/",
            "https://swapi-trybe.herokuapp.com/api/people/43/",
            "https://swapi-trybe.herokuapp.com/api/people/62/"
        ],
        "films": [
            "https://swapi-trybe.herokuapp.com/api/films/1/",
            "https://swapi-trybe.herokuapp.com/api/films/3/",
            "https://swapi-trybe.herokuapp.com/api/films/4/",
            "https://swapi-trybe.herokuapp.com/api/films/5/",
            "https://swapi-trybe.herokuapp.com/api/films/6/"
        ],
        "created": "2014-12-09T13:50:49.641000Z",
        "edited": "2014-12-20T20:58:18.411000Z",
        "url": "https://swapi-trybe.herokuapp.com/api/planets/1/"
    },
    {
        "name": "Alderaan",
        "rotation_period": "24",
        "orbital_period": "364",
        "diameter": "12500",
        "climate": "temperate",
        "gravity": "1 standard",
        "terrain": "grasslands, mountains",
        "surface_water": "40",
        "population": "2000000000",
        "residents": [
            "https://swapi-trybe.herokuapp.com/api/people/5/",
            "https://swapi-trybe.herokuapp.com/api/people/68/",
            "https://swapi-trybe.herokuapp.com/api/people/81/"
        ],
        "films": [
            "https://swapi-trybe.herokuapp.com/api/films/1/",
            "https://swapi-trybe.herokuapp.com/api/films/6/"
        ],
        "created": "2014-12-10T11:35:48.479000Z",
        "edited": "2014-12-20T20:58:18.420000Z",
        "url": "https://swapi-trybe.herokuapp.com/api/planets/2/"
    },
    {
        "name": "Yavin IV",
        "rotation_period": "24",
        "orbital_period": "4818",
        "diameter": "10200",
        "climate": "temperate, tropical",
        "gravity": "1 standard",
        "terrain": "jungle, rainforests",
        "surface_water": "8",
        "population": "1000",
        "residents": [],
        "films": [
            "https://swapi-trybe.herokuapp.com/api/films/1/"
        ],
        "created": "2014-12-10T11:37:19.144000Z",
        "edited": "2014-12-20T20:58:18.421000Z",
        "url": "https://swapi-trybe.herokuapp.com/api/planets/3/"
    },
    {
        "name": "Hoth",
        "rotation_period": "23",
        "orbital_period": "549",
        "diameter": "7200",
        "climate": "frozen",
        "gravity": "1.1 standard",
        "terrain": "tundra, ice caves, mountain ranges",
        "surface_water": "100",
        "population": "unknown",
        "residents": [],
        "films": [
            "https://swapi-trybe.herokuapp.com/api/films/2/"
        ],
        "created": "2014-12-10T11:39:13.934000Z",
        "edited": "2014-12-20T20:58:18.423000Z",
        "url": "https://swapi-trybe.herokuapp.com/api/planets/4/"
    },
    {
        "name": "Dagobah",
        "rotation_period": "23",
        "orbital_period": "341",
        "diameter": "8900",
        "climate": "murky",
        "gravity": "N/A",
        "terrain": "swamp, jungles",
        "surface_water": "8",
        "population": "unknown",
        "residents": [],
        "films": [
            "https://swapi-trybe.herokuapp.com/api/films/2/",
            "https://swapi-trybe.herokuapp.com/api/films/3/",
            "https://swapi-trybe.herokuapp.com/api/films/6/"
        ],
        "created": "2014-12-10T11:42:22.590000Z",
        "edited": "2014-12-20T20:58:18.425000Z",
        "url": "https://swapi-trybe.herokuapp.com/api/planets/5/"
    }
]